Metadata-Version: 2.1
Name: ivadomed
Version: 2.9.10
Summary: Feature conditioning for IVADO medical imaging project.
Home-page: https://github.com/neuropoly/ivadomed
Author: NeuroPoly and Mila
Author-email: none@none.com
Classifier: Development Status :: 3 - Alpha
Classifier: Intended Audience :: Developers
Classifier: Programming Language :: Python :: 3
Requires-Python: >=3.7,<3.11
License-File: LICENSE.md
Requires-Dist: csv-diff >=1.0
Requires-Dist: loguru ~=0.5
Requires-Dist: imageio >=2.31.4
Requires-Dist: joblib ~=1.0
Requires-Dist: matplotlib >=3.3.0
Requires-Dist: nibabel ~=5.2
Requires-Dist: onnx
Requires-Dist: onnxruntime !=1.16.0,>=1.7.0
Requires-Dist: pandas <2.0,>=1.1
Requires-Dist: pybids <0.15.6,>=0.14.0
Requires-Dist: scikit-learn >=0.20.3
Requires-Dist: scikit-image ~=0.17
Requires-Dist: seaborn ~=0.11
Requires-Dist: tensorboard >=1.15.0
Requires-Dist: tqdm >=4.30
Requires-Dist: scipy
Requires-Dist: torchio >=0.18.68
Requires-Dist: torch >=1.8.1
Requires-Dist: torchvision >=0.9.1
Requires-Dist: wandb >=0.12.11
Provides-Extra: contrib
Requires-Dist: pre-commit >=2.10.1 ; extra == 'contrib'
Requires-Dist: flake8 ; extra == 'contrib'
Provides-Extra: dev
Requires-Dist: csv-diff >=1.0 ; extra == 'dev'
Requires-Dist: loguru ~=0.5 ; extra == 'dev'
Requires-Dist: imageio >=2.31.4 ; extra == 'dev'
Requires-Dist: joblib ~=1.0 ; extra == 'dev'
Requires-Dist: matplotlib >=3.3.0 ; extra == 'dev'
Requires-Dist: nibabel ~=5.2 ; extra == 'dev'
Requires-Dist: onnx ; extra == 'dev'
Requires-Dist: onnxruntime !=1.16.0,>=1.7.0 ; extra == 'dev'
Requires-Dist: pandas <2.0,>=1.1 ; extra == 'dev'
Requires-Dist: pybids <0.15.6,>=0.14.0 ; extra == 'dev'
Requires-Dist: scikit-learn >=0.20.3 ; extra == 'dev'
Requires-Dist: scikit-image ~=0.17 ; extra == 'dev'
Requires-Dist: seaborn ~=0.11 ; extra == 'dev'
Requires-Dist: tensorboard >=1.15.0 ; extra == 'dev'
Requires-Dist: tqdm >=4.30 ; extra == 'dev'
Requires-Dist: scipy ; extra == 'dev'
Requires-Dist: torchio >=0.18.68 ; extra == 'dev'
Requires-Dist: torch >=1.8.1 ; extra == 'dev'
Requires-Dist: torchvision >=0.9.1 ; extra == 'dev'
Requires-Dist: wandb >=0.12.11 ; extra == 'dev'
Requires-Dist: sphinx ; extra == 'dev'
Requires-Dist: sphinx-rtd-theme ; extra == 'dev'
Requires-Dist: sphinx-tabs ; extra == 'dev'
Requires-Dist: sphinx-toolbox ; extra == 'dev'
Requires-Dist: sphinx-jsonschema ; extra == 'dev'
Requires-Dist: pypandoc ; extra == 'dev'
Requires-Dist: pytest ~=6.2 ; extra == 'dev'
Requires-Dist: pytest-cases ~=3.6.8 ; extra == 'dev'
Requires-Dist: pytest-cov ; extra == 'dev'
Requires-Dist: pytest-ordering ~=0.6 ; extra == 'dev'
Requires-Dist: pytest-console-scripts ~=1.1 ; extra == 'dev'
Requires-Dist: coverage ; extra == 'dev'
Requires-Dist: coveralls ; extra == 'dev'
Requires-Dist: pre-commit >=2.10.1 ; extra == 'dev'
Requires-Dist: flake8 ; extra == 'dev'
Provides-Extra: docs
Requires-Dist: sphinx ; extra == 'docs'
Requires-Dist: sphinx-rtd-theme ; extra == 'docs'
Requires-Dist: sphinx-tabs ; extra == 'docs'
Requires-Dist: sphinx-toolbox ; extra == 'docs'
Requires-Dist: sphinx-jsonschema ; extra == 'docs'
Requires-Dist: pypandoc ; extra == 'docs'
Provides-Extra: tests
Requires-Dist: pytest ~=6.2 ; extra == 'tests'
Requires-Dist: pytest-cases ~=3.6.8 ; extra == 'tests'
Requires-Dist: pytest-cov ; extra == 'tests'
Requires-Dist: pytest-ordering ~=0.6 ; extra == 'tests'
Requires-Dist: pytest-console-scripts ~=1.1 ; extra == 'tests'
Requires-Dist: coverage ; extra == 'tests'
Requires-Dist: coveralls ; extra == 'tests'
